KPZConfigurerView/__init__.py
KPZConfigurerView/interfaces_setting.py
KPZConfigurerView/widgets/__init__.py
KPZConfigurerView/widgets/action_calendar.py
KPZConfigurerView/widgets/base.py
KPZConfigurerView/widgets/colors.py
KPZConfigurerView/widgets/date.py
KPZConfigurerView/widgets/datetime.py
KPZConfigurerView/widgets/flag.py
KPZConfigurerView/widgets/id_.py
KPZConfigurerView/widgets/script_table.py
KPZConfigurerView/widgets/time.py
KPZConfigurerView-0.3.0.dist-info/METADATA
KPZConfigurerView-0.3.0.dist-info/WHEEL
KPZConfigurerView-0.3.0.dist-info/top_level.txt
KPZConfigurerView-0.3.0.dist-info/RECORD
